haitch/__about__.py
haitch/__init__.py
haitch/_attrs.py
haitch/_typing.py
haitch/py.typed
haitch/_components/__init__.py
haitch/_components/_html5.py
haitch/_elements/__init__.py
haitch/_elements/_element.py
haitch/_elements/_special/__init__.py
haitch/_elements/_special/_fragment.py
haitch/_elements/_special/_unsafe.py
haitch/_elements/_tags/__init__.py
haitch/_elements/_tags/_a.py
haitch/_elements/_tags/_abbr.py
haitch/_elements/_tags/_address.py
haitch/_elements/_tags/_area.py
haitch/_elements/_tags/_article.py
haitch/_elements/_tags/_aside.py
haitch/_elements/_tags/_audio.py
haitch/_elements/_tags/_b.py
haitch/_elements/_tags/_base.py
haitch/_elements/_tags/_bdi.py
haitch/_elements/_tags/_bdo.py
haitch/_elements/_tags/_blockquote.py
haitch/_elements/_tags/_body.py
haitch/_elements/_tags/_br.py
haitch/_elements/_tags/_button.py
haitch/_elements/_tags/_canvas.py
haitch/_elements/_tags/_caption.py
haitch/_elements/_tags/_cite.py
haitch/_elements/_tags/_code.py
haitch/_elements/_tags/_col.py
haitch/_elements/_tags/_colgroup.py
haitch/_elements/_tags/_data.py
haitch/_elements/_tags/_datalist.py
haitch/_elements/_tags/_dd.py
haitch/_elements/_tags/_del.py
haitch/_elements/_tags/_details.py
haitch/_elements/_tags/_dialog.py
haitch/_elements/_tags/_div.py
haitch/_elements/_tags/_dl.py
haitch/_elements/_tags/_dt.py
haitch/_elements/_tags/_em.py
haitch/_elements/_tags/_embed.py
haitch/_elements/_tags/_fieldset.py
haitch/_elements/_tags/_figcaption.py
haitch/_elements/_tags/_figure.py
haitch/_elements/_tags/_footer.py
haitch/_elements/_tags/_form.py
haitch/_elements/_tags/_h1.py
haitch/_elements/_tags/_h2.py
haitch/_elements/_tags/_h3.py
haitch/_elements/_tags/_h4.py
haitch/_elements/_tags/_h5.py
haitch/_elements/_tags/_h6.py
haitch/_elements/_tags/_head.py
haitch/_elements/_tags/_header.py
haitch/_elements/_tags/_hgroup.py
haitch/_elements/_tags/_hr.py
haitch/_elements/_tags/_html.py
haitch/_elements/_tags/_i.py
haitch/_elements/_tags/_img.py
haitch-0.12.1.dist-info/METADATA
haitch-0.12.1.dist-info/WHEEL
haitch-0.12.1.dist-info/licenses/LICENSE.txt
haitch-0.12.1.dist-info/RECORD
