Metadata-Version: 2.4
Name: haitch
Version: 0.12.1
Summary: simplify your HTML building.
Project-URL: Homepage, https://sr.ht/~loges/haitch
Project-URL: Source, https://git.sr.ht/~loges/haitch
Project-URL: Issues, https://todo.sr.ht/~loges/haitch
Author-email: Logan Connolly <me@loganconnolly.com>
License-Expression: BSD-3-Clause
License-File: LICENSE.txt
Classifier: Development Status :: 4 - Beta
Classifier: Operating System :: OS Independent
Classifier: Programming Language :: Python
Classifier: Programming Language :: Python :: 3.8
Classifier: Programming Language :: Python :: 3.9
Classifier: Programming Language :: Python :: 3.10
Classifier: Programming Language :: Python :: 3.11
Classifier: Programming Language :: Python :: 3.12
Classifier: Programming Language :: Python :: 3.13
Requires-Python: >=3.8
Requires-Dist: typing-extensions
